contrast_security/__init__.py
contrast_security/contrast_sdk.py
contrast_security/filters/__init__.py
contrast_security/filters/application_filter.py
contrast_security/filters/application_library_filter.py
contrast_security/filters/application_trace_filter.py
contrast_security/filters/filter_utils.py
contrast_security/filters/library_filter.py
contrast_security/filters/server_filter.py
contrast_security/filters/server_library_filter.py
contrast_security/filters/server_trace_filter.py
contrast_security/filters/trace_filter.py
contrast_security/filters/trace_time_to_remediate_filter.py
contrast_security/filters/trace_trend_filter.py
contrast_security/types/AgentTypes.py
contrast_security/types/__init__.py
contrast_security/user_api/__init__.py
contrast_security/user_api/alerts_api.py
contrast_security/user_api/api_support.py
contrast_security/user_api/application_api.py
contrast_security/user_api/history_api.py
contrast_security/user_api/library_api.py
contrast_security/user_api/modules_api.py
contrast_security/user_api/organization_api.py
contrast_security/user_api/policy_api.py
contrast_security/user_api/profile_api.py
contrast_security/user_api/response.py
contrast_security/user_api/role_api.py
contrast_security/user_api/route_coverage.py
contrast_security/user_api/scores_api.py
contrast_security/user_api/server_api.py
contrast_security/user_api/session_metadata_api.py
contrast_security/user_api/tags_api.py
contrast_security/user_api/trace_api.py
contrast_security/user_api/user_api.py
contrast_security/user_api/util.py
contrast_security/user_api/version.py
contrast_security/user_api/webhook_api.py
contrast_security-0.23.dist-info/METADATA
contrast_security-0.23.dist-info/WHEEL
contrast_security-0.23.dist-info/top_level.txt
contrast_security-0.23.dist-info/RECORD
