Metadata-Version: 2.1
Name: contrast-security
Version: 0.23
Summary: Module to easily interact with the Contrast api
Home-page: https://github.com/Contrast-Security-OSS/contrast-sdk-python
Author: Contrast Security
Author-email: integrations@contrastsecurity.com
License: UNKNOWN
Download-URL: https://github.com/Contrast-Security-OSS/contrast-sdk-python/releases
Keywords: contrast,security,iast,sast,rasp
Platform: UNKNOWN
Requires-Dist: requests
Requires-Dist: validators
